soboro/__init__.py
soboro/__main__.py
soboro/app.py
soboro/cli.py
soboro/exporter.py
soboro/runner.py
soboro/common/__init__.py
soboro/common/bbox.py
soboro/common/functions.py
soboro/common/image.py
soboro/common/status.py
soboro/common/types.py
soboro/models/__init__.py
soboro/models/fairmot/__init__.py
soboro/models/fairmot/model.py
soboro/models/fairmot/postproc.py
soboro/models/fairmot/preproc.py
soboro/models/icls/__init__.py
soboro/models/icls/model.py
soboro/models/icls/postproc.py
soboro/models/icls/preproc.py
soboro/models/onnx/__init__.py
soboro/models/onnx/cleaner.py
soboro/models/onnx/cli.py
soboro/models/onnx/runner.py
soboro/models/preproc/__init__.py
soboro/models/preproc/image.py
soboro/models/tsm/__init__.py
soboro/models/tsm/model.py
soboro/models/tsm/postproc.py
soboro/models/tsm/preproc.py
soboro/models/yolo5face/__init__.py
soboro/models/yolo5face/model.py
soboro/models/yolo5face/postproc.py
soboro/models/yolo5face/preproc.py
soboro/models/yolox/__init__.py
soboro/models/yolox/model.py
soboro/models/yolox/postproc.py
soboro/models/yolox/preproc.py
soboro/modules/__init__.py
soboro/modules/mot/__init__.py
soboro/modules/mot/bytetrack.py
soboro/modules/mot/kalman_filter.py
soboro/modules/mot/track.py
soboro/modules/odac/__init__.py
soboro/modules/odac/runner.py
soboro-0.0.5.dist-info/METADATA
soboro-0.0.5.dist-info/WHEEL
soboro-0.0.5.dist-info/entry_points.txt
soboro-0.0.5.dist-info/top_level.txt
soboro-0.0.5.dist-info/RECORD
