Metadata-Version: 2.1
Name: soboro
Version: 0.0.5
Summary: soboro
Home-page: UNKNOWN
Author: datnh21
Author-email: v.datnh21@vinai.io
License: UNKNOWN
Platform: UNKNOWN
Classifier: Programming Language :: Python :: 3
Classifier: License :: OSI Approved :: MIT License
Classifier: Operating System :: OS Independent
Requires-Python: >=3.6
Requires-Dist: onnx
Requires-Dist: onnxsim
Requires-Dist: cowsay
Requires-Dist: numpy
Requires-Dist: opencv-python
Requires-Dist: mousse
Requires-Dist: typer
Requires-Dist: scipy
Requires-Dist: onnxruntime
Requires-Dist: black
Provides-Extra: all
Requires-Dist: onnx ; extra == 'all'
Requires-Dist: onnxsim ; extra == 'all'
Requires-Dist: numpy ; extra == 'all'
Requires-Dist: onnxruntime ; extra == 'all'
Requires-Dist: opencv-python ; extra == 'all'
Provides-Extra: onnx
Requires-Dist: onnx ; extra == 'onnx'
Requires-Dist: onnxruntime ; extra == 'onnx'
Requires-Dist: onnxsim ; extra == 'onnx'
Provides-Extra: preproc
Requires-Dist: numpy ; extra == 'preproc'
Requires-Dist: opencv-python ; extra == 'preproc'
Provides-Extra: yolox
Requires-Dist: numpy ; extra == 'yolox'
